AutomataPractical/FiniteAutomate.py
AutomataPractical/TuringMachine.py
AutomataPractical/__init__.py
AutomatePractical-0.2.dist-info/METADATA
AutomatePractical-0.2.dist-info/WHEEL
AutomatePractical-0.2.dist-info/top_level.txt
AutomatePractical-0.2.dist-info/RECORD
