Metadata-Version: 2.1
Name: AutomatePractical
Version: 0.2
Summary: My automation tools
